autoname/__init__.py
autoname/py.typed
autoname-2.1.0.dist-info/LICENSE.md
autoname-2.1.0.dist-info/METADATA
autoname-2.1.0.dist-info/WHEEL
autoname-2.1.0.dist-info/RECORD
