Metadata-Version: 2.1
Name: autoname
Version: 2.1.0
Summary: an enum `AutoName` from python docs with multiple stringcase options
Home-page: https://github.com/wasdee/autoname
License: ISC
Author: Nutchanon Ninyawee
Author-email: me@nutchanon.org
Requires-Python: >=3.7,<4.0
Classifier: License :: OSI Approved
Classifier: Programming Language :: Python :: 3
Classifier: Programming Language :: Python :: 3.7
Classifier: Programming Language :: Python :: 3.8
Classifier: Programming Language :: Python :: 3.9
Classifier: Programming Language :: Python :: 3.10
Classifier: Programming Language :: Python :: 3.11
Project-URL: Repository, https://github.com/wasdee/autoname
